[{"id":1,"name":"庞金民","telephone":13644225789,"theWin":"恭喜你！获得了50元话费！"},{"id":2,"name":"陈泳彬","telephone":13644225789,"theWin":"恭喜你！获得了50元话费！"},{"id":3,"name":"陈滓轩","telephone":13644225789,"theWin":"恭喜你！获得了100元话费！"},{"id":4,"name":"庞金民","telephone":13644225789,"theWin":"恭喜你！获得了20元话费！"},{"id":5,"name":"林峰","telephone":11550508080,"theWin":"恭喜你！获得了100元话费！"},{"id":6,"name":"陈某某","telephone":15768319869,"theWin":"恭喜你！获得了20元话费！"},{"id":7,"name":"陈生","telephone":12333331123,"theWin":"恭喜你！获得了50元话费！"},{"id":8,"name":"ice","telephone":12312312311,"theWin":"恭喜你！获得了100元话费！"}]